cli/__init__.py
cli/client.py
cli/commands.py
cli/config.py
cli/printers.py
quicksplit-1.4.dist-info/METADATA
quicksplit-1.4.dist-info/WHEEL
quicksplit-1.4.dist-info/entry_points.txt
quicksplit-1.4.dist-info/top_level.txt
quicksplit-1.4.dist-info/RECORD
