Metadata-Version: 2.1
Name: quicksplit
Version: 1.4
Summary: The developer tool for fast, easy A/B tests
Home-page: UNKNOWN
Author: Quick Split
Author-email: tom@quicksplit.io
License: UNKNOWN
Platform: UNKNOWN
Classifier: Programming Language :: Python :: 3
Classifier: License :: OSI Approved :: MIT License
Classifier: Operating System :: OS Independent
Requires-Python: >=3.7
Requires-Dist: click (==7.0)
Requires-Dist: requests (==2.23.0)
Requires-Dist: terminaltables (==3.1.0)
